[
  {
    "rss": "https://front-rss.herokuapp.com/coronavirus/caixin",
    "title": "武汉肺炎防疫全纪录(财新网)",
    "link": "http://m.app.caixin.com/m_topic_detail/1473.html",
    "items": []
  },
  {
    "rss": "https://front-rss.herokuapp.com/coronavirus/dxy",
    "title": "全国新型肺炎疫情实时动态(丁香园)",
    "link": "https://3g.dxy.cn/newh5/view/pneumonia",
    "items": []
  },
  {
    "rss": "https://front-rss.herokuapp.com/wechat/ershicimi/9891",
    "title": "Vue社区",
    "link": "https://www.ershicimi.com/a/9891",
    "items": []
  },
  {
    "rss": "https://front-rss.herokuapp.com/wechat/ershicimi/10315",
    "title": "Vue中文社区",
    "link": "https://www.ershicimi.com/a/10315",
    "items": [
      {
        "title": "174道JavaScript 面试知识点总结（上）",
        "link": "https://www.ershicimi.com/p/959c468c1e5273534815a5c4d49cbc36",
        "date": "2021-03-18"
      },
      {
        "title": "设计灵感：12 个注册登录页面设计",
        "link": "https://www.ershicimi.com/p/9a5c17c6255dde8aee91aeabd5b72db8",
        "date": "2021-03-18"
      },
      {
        "title": "小程序变现效率大幅提升，实战指南奉上",
        "link": "https://www.ershicimi.com/p/98ed89f051ddb4372b18c9af929b499b",
        "date": "2021-03-17"
      },
      {
        "title": "开发中经常遇到的JavaScript问题整理（超实用）",
        "link": "https://www.ershicimi.com/p/5dae011bbc8e84b730d0b97ae84f1e0a",
        "date": "2021-03-17"
      },
      {
        "title": "快速上手Token登录认证",
        "link": "https://www.ershicimi.com/p/6109d412c1d18dd130ae0f02d93ab7dc",
        "date": "2021-03-17"
      },
      {
        "title": "不读前端源码的你，并不清楚自己错过了什么？",
        "link": "https://www.ershicimi.com/p/56e04f11b2b4e1e133f3c8a9cc897608",
        "date": "2021-03-16"
      },
      {
        "title": "面试官问 Vue 性能优化，我该怎么回答",
        "link": "https://www.ershicimi.com/p/6091719dc293ab17218d3f3da7fbeacc",
        "date": "2021-03-16"
      },
      {
        "title": "谈谈 JavaScript 中的类型转换机制",
        "link": "https://www.ershicimi.com/p/127a1bf68fcca1b6960e9741bc2cd0f2",
        "date": "2021-03-16"
      },
      {
        "title": "前端工程化自学指南，高级前端必备",
        "link": "https://www.ershicimi.com/p/36160cae593e968ebd06845d41721404",
        "date": "2021-03-15"
      },
      {
        "title": "Vue3组件库工程化实战 --Element3",
        "link": "https://www.ershicimi.com/p/a0b46d7a34975ddf60c92d12064702ff",
        "date": "2021-03-15"
      },
      {
        "title": "2020 JavaScript明星项目",
        "link": "https://www.ershicimi.com/p/27e805e85374c16caa86f17235e0e7a2",
        "date": "2021-03-15"
      },
      {
        "title": "微信3.0来了，用电脑刷朋友圈是一种什么样的体验（内含内测版下载链接）",
        "link": "https://www.ershicimi.com/p/abfd68bf4be189dd7572c12df4b14a17",
        "date": "2021-03-13"
      },
      {
        "title": "VS Code 插件开发入门教程",
        "link": "https://www.ershicimi.com/p/a555e9030ffe442d8f74705af996f041",
        "date": "2021-03-13"
      },
      {
        "title": "程序员如果想要进阶年薪 50 万，需要掌握的能力是什么？",
        "link": "https://www.ershicimi.com/p/fd0b60eda30fb33a2f5ab9f5e4b65384",
        "date": "2021-03-12"
      },
      {
        "title": "尤雨溪：下一代前端构建工具 ViteJS 技术解读",
        "link": "https://www.ershicimi.com/p/15a2e001ec3e1929aff93a2d014b1094",
        "date": "2021-03-12"
      },
      {
        "title": "30个编程领域的趣图",
        "link": "https://www.ershicimi.com/p/a3c221297cf51d3713ab252d539c131e",
        "date": "2021-03-12"
      },
      {
        "title": "深入浅出前端本地储存",
        "link": "https://www.ershicimi.com/p/2b34bccc0708de0ccdf3bbe8520972a2",
        "date": "2021-03-11"
      },
      {
        "title": "Javscript字符串常用方法总结",
        "link": "https://www.ershicimi.com/p/0e559c931ad8bba715b13f9cb0b09eda",
        "date": "2021-03-11"
      },
      {
        "title": "Javscript字符串常用方法总结",
        "link": "https://www.ershicimi.com/p/81e165ca2c1233ddd46ed1f8b52009e4",
        "date": "2021-03-11"
      },
      {
        "title": "刚刚！腾讯官宣前端人才这样选",
        "link": "https://www.ershicimi.com/p/8f766d0c4303c3debf46188f60e599a8",
        "date": "2021-03-10"
      }
    ]
  },
  {
    "rss": "https://front-rss.herokuapp.com/wechat/ershicimi/10646",
    "title": "VUE全家桶",
    "link": "https://www.ershicimi.com/a/10646",
    "items": []
  },
  {
    "rss": "https://front-rss.herokuapp.com/wechat/ershicimi/10445",
    "title": "React中文社区",
    "link": "https://www.ershicimi.com/a/10445",
    "items": [
      {
        "title": "招个数据分析工程师，我给25k",
        "link": "https://www.ershicimi.com/p/003c2b9ee98c0992b36c5258e82747d3",
        "date": "2020-08-19"
      },
      {
        "title": "V8是如何执行一段JS代码的？",
        "link": "https://www.ershicimi.com/p/cb16aeed88d6f02c5e6575abe6e48a78",
        "date": "2020-07-14"
      },
      {
        "title": "一文掌握GO语言实战技能(三)",
        "link": "https://www.ershicimi.com/p/46cac625ac351e226dc4486f2397cb50",
        "date": "2020-05-18"
      },
      {
        "title": "一文掌握GO语言实战技能(二)",
        "link": "https://www.ershicimi.com/p/0efd18d6a0774aa88db09fc12989a6ab",
        "date": "2020-05-17"
      },
      {
        "title": "虚幻引擎5官方视频",
        "link": "https://www.ershicimi.com/p/28d9c0c525557fe3effbfffa6d76350b",
        "date": "2020-05-17"
      },
      {
        "title": "一文掌握GO语言实战技能(一) - 万字长文",
        "link": "https://www.ershicimi.com/p/b4aa653a71762c4ac0d8fb3a4d4d1c63",
        "date": "2020-05-15"
      },
      {
        "title": "一文达到Mysql实战水平-习题答案",
        "link": "https://www.ershicimi.com/p/541e3bf6cc03ebd608c403da8cd4f8d3",
        "date": "2020-05-14"
      },
      {
        "title": "一文达到Mysql实战水平",
        "link": "https://www.ershicimi.com/p/f0acfb4c01e6e94632d6f778ab0e7048",
        "date": "2020-05-13"
      },
      {
        "title": "一文掌握Linux实战技能-系统管理篇",
        "link": "https://www.ershicimi.com/p/c0928c6788d3cd2b151112bdc46af9f8",
        "date": "2020-05-12"
      },
      {
        "title": "一文掌握linux实战技能-系统操作篇",
        "link": "https://www.ershicimi.com/p/0834d78171ab978846a1826781cd4f8c",
        "date": "2020-05-11"
      },
      {
        "title": "双12，送33本前端书籍回馈大家及珍藏已久的几个公众号",
        "link": "https://www.ershicimi.com/p/8d6efb9786a98f2f9682e6bea7bcff88",
        "date": "2019-12-15"
      },
      {
        "title": "一文深度剖析Axios源码",
        "link": "https://www.ershicimi.com/p/22f3dc65afaa70adb95ed48cc610af4a",
        "date": "2019-12-11"
      },
      {
        "title": "来自蚂蚁金服的前端项目最佳实践",
        "link": "https://www.ershicimi.com/p/aae2f8cef34dd39021c9bd7050993a7c",
        "date": "2019-11-28"
      },
      {
        "title": "一文掌握Webpack编译流程",
        "link": "https://www.ershicimi.com/p/a47e055b404be5ccb5898cd673c569c6",
        "date": "2019-11-25"
      },
      {
        "title": "你不知道的 React Diff",
        "link": "https://www.ershicimi.com/p/fed1c7a38e6ef4b3dfa335a135b8c090",
        "date": "2019-11-15"
      },
      {
        "title": "推荐几个公众号",
        "link": "https://www.ershicimi.com/p/a3828f970288d59160cda21828777128",
        "date": "2019-11-15"
      },
      {
        "title": "Javascript条件逻辑设计重构",
        "link": "https://www.ershicimi.com/p/37d7e7bbf0991fadb887575b894b8ee4",
        "date": "2019-11-14"
      },
      {
        "title": "推荐几个公众号",
        "link": "https://www.ershicimi.com/p/126b6a8d127d2a6f3eb0af6fb8a72a45",
        "date": "2019-11-14"
      },
      {
        "title": "Javascript 实现优雅的链式取值",
        "link": "https://www.ershicimi.com/p/0197eec9b690ae8c75f91ec7afac7baa",
        "date": "2019-11-06"
      },
      {
        "title": "实战LeetCode - 前端面试必备二叉树算法",
        "link": "https://www.ershicimi.com/p/f3413b58491ac20f4c17a09b8a0af5e1",
        "date": "2019-10-31"
      }
    ]
  },
  {
    "rss": "https://front-rss.herokuapp.com/wechat/ershicimi/5760",
    "title": "前端早读课",
    "link": "https://www.ershicimi.com/a/5760",
    "items": []
  },
  {
    "rss": "https://front-rss.herokuapp.com/wechat/ershicimi/65",
    "title": "前端大全",
    "link": "https://www.ershicimi.com/a/65",
    "items": [
      {
        "title": "对比了React17和Vue3后，总结了这些面试可用的亮点",
        "link": "https://www.ershicimi.com/p/2449835c5e13b3aa6c0837c5aceb1ab1",
        "date": "2021-03-17"
      },
      {
        "title": "你不知道的 Proxy",
        "link": "https://www.ershicimi.com/p/925871f3fc77f899a1e1ce9a55c03519",
        "date": "2021-03-17"
      },
      {
        "title": "前端每日一题 #49",
        "link": "https://www.ershicimi.com/p/6971b3c5242e94c45b39aa3017547ccb",
        "date": "2021-03-17"
      },
      {
        "title": "设计灵感：12 个注册登录页面设计",
        "link": "https://www.ershicimi.com/p/0603e3ae411e95ba807bd165f39a932c",
        "date": "2021-03-17"
      },
      {
        "title": "前端性能优化 24 条建议",
        "link": "https://www.ershicimi.com/p/64b30bdd8d7b97e76e641e9f974f1554",
        "date": "2021-03-16"
      },
      {
        "title": "Node.js 中的异步 Generator 函数和 Websockets",
        "link": "https://www.ershicimi.com/p/0de51a92014b71d144ef28e6ebb80a6e",
        "date": "2021-03-16"
      },
      {
        "title": "前端每日一题 #48",
        "link": "https://www.ershicimi.com/p/e6ec078606385bff535f6d7d27f4c599",
        "date": "2021-03-16"
      },
      {
        "title": "设计灵感：12 组运用流体渐变的页面设计",
        "link": "https://www.ershicimi.com/p/b4b599659142fb350c02a1da7ddd35ac",
        "date": "2021-03-16"
      },
      {
        "title": "「React缓存页面」从需求到开源（我是怎么样让产品小姐姐刮目相看的",
        "link": "https://www.ershicimi.com/p/cf47dd4071e1e93628d81fbb3d6071ea",
        "date": "2021-03-15"
      },
      {
        "title": "three.js 实现露珠滴落动画",
        "link": "https://www.ershicimi.com/p/b38da6ab54e127ade7c0efa8c1c31caa",
        "date": "2021-03-15"
      },
      {
        "title": "前端每日一题 #47",
        "link": "https://www.ershicimi.com/p/210949458b71453a5b8876de51ab1764",
        "date": "2021-03-15"
      },
      {
        "title": "设计灵感：12组存储空间APP界面设计",
        "link": "https://www.ershicimi.com/p/8313717c704ed7e59b39bcf4678a3000",
        "date": "2021-03-15"
      },
      {
        "title": "「前端工程化」从0-1搭建 React，TS 脚手架",
        "link": "https://www.ershicimi.com/p/5d54a84fd539a4df498050109bd0e196",
        "date": "2021-03-13"
      },
      {
        "title": "Chrome 89 新功能一览，性能提升明显，大量 DevTools 新特性！",
        "link": "https://www.ershicimi.com/p/ae968d313b06723a82c785b190ce71f3",
        "date": "2021-03-13"
      },
      {
        "title": "前端每日一题 #46",
        "link": "https://www.ershicimi.com/p/92e1d8f45a5af4f54e90b3301ed10f43",
        "date": "2021-03-13"
      },
      {
        "title": "设计灵感：12组金融理财类App界面设计",
        "link": "https://www.ershicimi.com/p/032593c5b9443ac55dad5af333be30af",
        "date": "2021-03-13"
      },
      {
        "title": "北漂6年，年薪50W+，他说自己具备了这 3个能力",
        "link": "https://www.ershicimi.com/p/c105dbd48179ac310480004d586d4fbc",
        "date": "2021-03-12"
      },
      {
        "title": "toFixed 函数引起的 bug",
        "link": "https://www.ershicimi.com/p/ecfd87d57ab9a326fefd01fa92d5acff",
        "date": "2021-03-12"
      },
      {
        "title": "前端每日一题 #45",
        "link": "https://www.ershicimi.com/p/9e5d6cb053d7097e4be12d773445262c",
        "date": "2021-03-12"
      },
      {
        "title": "设计灵感：一组画廊与博物馆App界面设计",
        "link": "https://www.ershicimi.com/p/626eea19b343b7146c7d37f8b23bef5b",
        "date": "2021-03-12"
      }
    ]
  },
  {
    "rss": "https://front-rss.herokuapp.com/wechat/ershicimi/29",
    "title": "前端开发",
    "link": "https://www.ershicimi.com/a/29",
    "items": []
  },
  {
    "rss": "https://front-rss.herokuapp.com/wechat/ershicimi/166",
    "title": "前端圈",
    "link": "https://www.ershicimi.com/a/166",
    "items": [
      {
        "title": "[视频]蒋豪群聊聊Vue 3 周边项目",
        "link": "https://www.ershicimi.com/p/2a12d97dd7bb04af90078ddf2b9f196d",
        "date": "2020-06-17"
      },
      {
        "title": "Vue3三连发，这期聊聊Vue 3周边项目",
        "link": "https://www.ershicimi.com/p/97695ac09543799ef0ccda9e2479572e",
        "date": "2020-06-08"
      },
      {
        "title": "[视频]Winter 教你 MVVM",
        "link": "https://www.ershicimi.com/p/407d00f5a91b47a7f16018aaec12084f",
        "date": "2020-05-13"
      },
      {
        "title": "约吗？ Winter 问你",
        "link": "https://www.ershicimi.com/p/56070921db6716af5615b24f68ab643b",
        "date": "2020-05-09"
      },
      {
        "title": "[视频]Vue.js 3.0 什么时候可以投入生产使用",
        "link": "https://www.ershicimi.com/p/62da65e218585b265a4ddc89ca674b0b",
        "date": "2020-04-27"
      },
      {
        "title": "尤雨溪约你聊聊Vue.js 3.0 Beta",
        "link": "https://www.ershicimi.com/p/6f88eda2cef2ca14858c173412919f36",
        "date": "2020-04-20"
      },
      {
        "title": "用JS重塑复古计算机艺术 @JSConf2019",
        "link": "https://www.ershicimi.com/p/acf2b5d2f1aaf1358cb1687279dc8d5f",
        "date": "2019-11-06"
      },
      {
        "title": "玉伯：我的前端成长之路",
        "link": "https://www.ershicimi.com/p/8e52b0d699f255b54e760cccca46bc4e",
        "date": "2019-11-05"
      },
      {
        "title": "[视频]刘帅带来《巨型小程序的分布式开发与自动化管理》！",
        "link": "https://www.ershicimi.com/p/87eba2f1f542935fbe26bfe7c5de69d5",
        "date": "2019-10-13"
      },
      {
        "title": "[更新视频]围观王泽在第五届FEDAY的演讲视频！",
        "link": "https://www.ershicimi.com/p/f249e57512400a250ea14690a5a5959d",
        "date": "2019-10-13"
      },
      {
        "title": "[视频]贵重带来《钉钉前端团队演进之路》！",
        "link": "https://www.ershicimi.com/p/c8c7fa8831fa6a691667b562d12be93b",
        "date": "2019-10-12"
      },
      {
        "title": "[视频]崔红保带来《基于weex实现的小程序引擎》！",
        "link": "https://www.ershicimi.com/p/c26e28939407871c257a92873da7c97b",
        "date": "2019-10-11"
      },
      {
        "title": "[视频]围观Unbug Lee在第五届FEDAY的演讲！",
        "link": "https://www.ershicimi.com/p/bd33a2fc61a62cf90655be0a334a708a",
        "date": "2019-10-10"
      },
      {
        "title": "[视频]围观周俊鹏《依托云的Serverless落地实践》！",
        "link": "https://www.ershicimi.com/p/313049037be2d335de0b13d1f010d9f0",
        "date": "2019-10-09"
      },
      {
        "title": "[视频]围观王泽在第五届FEDAY的演讲视频！",
        "link": "https://www.ershicimi.com/p/81e513aa228a3ab5a856e7900a27f8ed",
        "date": "2019-10-08"
      },
      {
        "title": "[视频]Chris Fritz在第五届FEDAY的演讲视频来啦！",
        "link": "https://www.ershicimi.com/p/4f543be7781c25a1563088c027f79138",
        "date": "2019-09-30"
      },
      {
        "title": "[视频]一起围观月影在第五届FEDAY的演讲！",
        "link": "https://www.ershicimi.com/p/42d368665250dce21db5c6c458b7f13a",
        "date": "2019-09-29"
      },
      {
        "title": "JavaScript性能开销之2019",
        "link": "https://www.ershicimi.com/p/e1ad32504936e36d4beeeb1bf021f19d",
        "date": "2019-07-09"
      },
      {
        "title": "[视频]探索Web编程的另一种形态@天翔",
        "link": "https://www.ershicimi.com/p/b553e23449fdde2afb6c75ca0491ba7d",
        "date": "2019-07-02"
      },
      {
        "title": "[视频]Vue开发小程序之性能优化@崔红保",
        "link": "https://www.ershicimi.com/p/4e4bc88e18647787e60afdbef9550dc0",
        "date": "2019-06-21"
      }
    ]
  },
  {
    "rss": "https://front-rss.herokuapp.com/wechat/ershicimi/169",
    "title": "前端开发博客",
    "items": [
      {
        "title": "vue 源码系列之 Dep 和 Watcher 的关系",
        "link": "https://www.ershicimi.com/p/65bf10375b2afe5dd943af39b03aeba8",
        "date": "2020-03-02"
      },
      {
        "title": "vue 源码系列之 watch 第二篇",
        "link": "https://www.ershicimi.com/p/4d515409885a1e0e0155f191ea809602",
        "date": "2020-03-01"
      },
      {
        "title": "vue 源码系列之 watch",
        "link": "https://www.ershicimi.com/p/257852039be039d97d469bca4ab65c36",
        "date": "2020-02-29"
      },
      {
        "title": "vue 源码系列之 computed",
        "link": "https://www.ershicimi.com/p/c3c1c798f14f413383d48a4c1ea8216c",
        "date": "2020-02-26"
      },
      {
        "title": "阿里 fusion 组件之 tab",
        "link": "https://www.ershicimi.com/p/3816d84b9fc881f8f67be958f531b4ba",
        "date": "2020-02-25"
      },
      {
        "title": "阿里 fusion 组件之 loading 第二篇",
        "link": "https://www.ershicimi.com/p/cb9e19d09f7b45caba1d47bc7f64da16",
        "date": "2020-02-21"
      },
      {
        "title": "阿里 fusion 组件之 loading",
        "link": "https://www.ershicimi.com/p/15be28914305f084bca8e7cc4fa665ee",
        "date": "2020-02-20"
      },
      {
        "title": "阿里 fusion 组件之 breadcrumb 第二篇",
        "link": "https://www.ershicimi.com/p/a55a9cc13c99126b048168031c8b49ce",
        "date": "2020-02-18"
      },
      {
        "title": "[webpack] Scope Hoisting",
        "link": "https://www.ershicimi.com/p/77632bc7cbc490c22556d88785034320",
        "date": "2020-02-16"
      },
      {
        "title": "阿里 ice.work 探秘系列 如何封装一个 useRequest",
        "link": "https://www.ershicimi.com/p/bdf27b012543afa8bfd2f810686403de",
        "date": "2020-02-14"
      },
      {
        "title": "[工具控]hoist-non-react-statics 你没用过吧",
        "link": "https://www.ershicimi.com/p/bb1161f2239a80f5e1b16357546ee040",
        "date": "2020-02-13"
      },
      {
        "title": "[工具控] react 优化里面用到 lodash.memoize",
        "link": "https://www.ershicimi.com/p/8030f9ceac2221818a92f0a24cede590",
        "date": "2020-02-12"
      },
      {
        "title": "[工具控]babel-react-optimize",
        "link": "https://www.ershicimi.com/p/87be70d3d4719eedb42df24f6303ca69",
        "date": "2020-02-11"
      },
      {
        "title": "[工具控来看看]代码高亮必备",
        "link": "https://www.ershicimi.com/p/56debedff7f9d3c357f3621de7a64aa2",
        "date": "2020-02-07"
      },
      {
        "title": "阿里 ice.work 探秘系列 react-materials 之Label",
        "link": "https://www.ershicimi.com/p/41048b591220c58f73c8e9945b1514c1",
        "date": "2020-02-06"
      },
      {
        "title": "阿里 ice.work 探秘系列 Auth 组件",
        "link": "https://www.ershicimi.com/p/fded8d3c703156437b5bb420eadd949e",
        "date": "2020-02-05"
      },
      {
        "title": "阿里 ice.work 探秘系列 css-hot-loader",
        "link": "https://www.ershicimi.com/p/3a72f27dcb1c69bf1a2020a5865a4497",
        "date": "2020-02-04"
      },
      {
        "title": "阿里 ice.work 探秘系列 disabled-reload",
        "link": "https://www.ershicimi.com/p/51eed11abceaabb3dd7f2ceed864d182",
        "date": "2020-02-03"
      },
      {
        "title": "阿里 ice.work 探秘系列 withRouter 的使用",
        "link": "https://www.ershicimi.com/p/29c023dd30374ab258ceef6aeaddb1e2",
        "date": "2020-01-16"
      },
      {
        "title": "阿里 ice.work 探秘系列 useState、useEffect",
        "link": "https://www.ershicimi.com/p/23159dcf23f0f8f92efd0a91c7a316f2",
        "date": "2020-01-15"
      }
    ],
    "link": "https://www.ershicimi.com/a/169"
  },
  {
    "rss": "https://front-rss.herokuapp.com/wechat/ershicimi/892",
    "title": "前端大学",
    "items": [],
    "link": "https://www.ershicimi.com/a/892"
  },
  {
    "rss": "https://front-rss.herokuapp.com/wechat/ershicimi/895",
    "title": "前端外刊评论",
    "items": [
      {
        "title": "字节跳动-广告研发 | 2021秋季校园人才召集令！",
        "link": "https://www.ershicimi.com/p/2358db3b947642bb5adffd571bca1614",
        "date": "2020-09-02"
      },
      {
        "title": "前端智能化实践——从图片识别UI样式",
        "link": "https://www.ershicimi.com/p/d6b4d4f61c3d7f036776be1b0668374b",
        "date": "2020-09-01"
      },
      {
        "title": "前阿里手淘前端负责人@winter：前端人如何保持竞争力？",
        "link": "https://www.ershicimi.com/p/9ee51370746c067d707a2937c53e3a5d",
        "date": "2020-08-27"
      },
      {
        "title": "付费课都免费？拉勾7周年把价值4000+的专栏免费了！！！",
        "link": "https://www.ershicimi.com/p/533e78a14587491d9c6f2c82be3c8f04",
        "date": "2020-07-20"
      },
      {
        "title": "深入理解 Angular 编译器",
        "link": "https://www.ershicimi.com/p/339a2b6718dbb4e7a278ea29c1d0eca5",
        "date": "2020-07-16"
      },
      {
        "title": "美团2021届移动端提前批招聘启动！",
        "link": "https://www.ershicimi.com/p/82d99851264b0cc69199504192ed1665",
        "date": "2020-07-16"
      },
      {
        "title": "1元福利 | 深度剖析Vue .js 3.0底层逻辑，带你向高级前端进阶！",
        "link": "https://www.ershicimi.com/p/b7eeaaa6276d65ebe0a5252368725728",
        "date": "2020-07-07"
      },
      {
        "title": "那些你应该考虑卸载的 VSCode 扩展",
        "link": "https://www.ershicimi.com/p/ceb06dae74e37bbe20f5d52f1ad5a2c4",
        "date": "2020-04-20"
      },
      {
        "title": "2020年 4 月 21日 星期二 晚上 9:30 Vue.js 作者尤雨溪与你相约前端圈的 B 站",
        "link": "https://www.ershicimi.com/p/69d20f9c5bb2de3da1dad85699594815",
        "date": "2020-04-19"
      },
      {
        "title": "ali-react-table：高性能 React 表格组件",
        "link": "https://www.ershicimi.com/p/4aeff96a51a674d7a02add3f8bd49c11",
        "date": "2020-04-16"
      },
      {
        "title": "nodejs事件循环阶段之定时器",
        "link": "https://www.ershicimi.com/p/f81c5d14b2fcd013d74096bdc3b8371c",
        "date": "2020-04-07"
      },
      {
        "title": "同学，你有一份阿里前端终面官分享的校招秘籍待查收",
        "link": "https://www.ershicimi.com/p/bd7626d5d7f18dded6a2a700d40f519b",
        "date": "2020-04-07"
      },
      {
        "title": "Sigi Framework 介绍",
        "link": "https://www.ershicimi.com/p/f51055685393a0ab66a73470183ce1e2",
        "date": "2020-02-17"
      },
      {
        "title": "字节跳动招聘 | 和优秀的人，做有挑战的事！",
        "link": "https://www.ershicimi.com/p/2589ee6a2550c6bf0177ff3ebfa24ff4",
        "date": "2020-02-10"
      },
      {
        "title": "使用Vue 3.0做JSX(TSX)风格的组件开发",
        "link": "https://www.ershicimi.com/p/2d916acf07e274201dfb59d19a4e31a2",
        "date": "2020-01-19"
      },
      {
        "title": "从敲下一行JS代码到这行代码被执行，中间发生了什么？",
        "link": "https://www.ershicimi.com/p/9712821caf5ac7b2e19b1f1ea0be56fc",
        "date": "2020-01-13"
      },
      {
        "title": "云凤蝶自由画布之道：分层模型",
        "link": "https://www.ershicimi.com/p/6f2ab75cf5c42cacddea1cab8ac43504",
        "date": "2020-01-02"
      },
      {
        "title": "从 VSCode 看大型 IDE 技术架构",
        "link": "https://www.ershicimi.com/p/191a6a52cf1d7cda4efe2f86817393c5",
        "date": "2019-12-18"
      },
      {
        "title": "SEE Conf 大会邀请函 | 体验美好，玩转数据",
        "link": "https://www.ershicimi.com/p/67d19ca247e5a4fe5268764036a43486",
        "date": "2019-12-18"
      },
      {
        "title": "准备好，力扣官方 App 来了！",
        "link": "https://www.ershicimi.com/p/c6a048c75bad1f9f7f8356f5f7cf08ab",
        "date": "2019-12-16"
      }
    ],
    "link": "https://www.ershicimi.com/a/895"
  },
  {
    "rss": "https://front-rss.herokuapp.com/wechat/ershicimi/154",
    "title": "前端之巅",
    "link": "https://www.ershicimi.com/a/154",
    "items": [
      {
        "title": "前端开发者必备的12个工具",
        "link": "https://www.ershicimi.com/p/3885f01ef5e406fb892c633b218f1ba6",
        "date": "2021-03-15"
      },
      {
        "title": "面对不断增长的业务规模，如何打破前端效率瓶颈？| GMTC",
        "link": "https://www.ershicimi.com/p/36dc5dd520b5ab8d49f675e0cdf309f8",
        "date": "2021-03-15"
      },
      {
        "title": "TypeScript 手册重写发布；阿里内网离职帖引热议，员工吐槽人不如驴；联想 CEO 支持反对",
        "link": "https://www.ershicimi.com/p/73f64139ac2d21e4ae53a24a6e78ad9d",
        "date": "2021-03-14"
      },
      {
        "title": "Angular、React 和 Vue 三大框架，Web 开发该如何选择？",
        "link": "https://www.ershicimi.com/p/694a33cfabc274ce682aa6f917ea8920",
        "date": "2021-03-12"
      },
      {
        "title": "盘点世界上 6 种奇怪的编程语言",
        "link": "https://www.ershicimi.com/p/a24709a9d86d0ffa38954de586b9ac65",
        "date": "2021-03-12"
      },
      {
        "title": "字节跳动、美团、阿里等国内大公司的 200+ 技术干货视频，任你选 | 活动推荐",
        "link": "https://www.ershicimi.com/p/2aff6bd68b5bffede3f84395069e1105",
        "date": "2021-03-12"
      },
      {
        "title": "2021年，原生永不为奴还是PWA绝地反击？",
        "link": "https://www.ershicimi.com/p/1e7e4ea046c0553192cfe52031db6ee0",
        "date": "2021-03-10"
      },
      {
        "title": "要改掉的 10 种 TypeScript 坏习惯",
        "link": "https://www.ershicimi.com/p/83e9c39c5ff0b715a59a113dec4a873d",
        "date": "2021-03-10"
      },
      {
        "title": "70% 的程序员，不懂数据结构和算法！ | 活动推荐",
        "link": "https://www.ershicimi.com/p/55c59ed6e86319917281fe4c624595d6",
        "date": "2021-03-10"
      },
      {
        "title": "Flutter 将成为未来 Ubuntu 应用程序的默认选择",
        "link": "https://www.ershicimi.com/p/2b93867f922445c33c3ab0014483a176",
        "date": "2021-03-08"
      },
      {
        "title": "15+人团队的前端体系架构应该如何管理？",
        "link": "https://www.ershicimi.com/p/dd2e103a8940ff8103895864f0af346f",
        "date": "2021-03-08"
      },
      {
        "title": "一套代码、多端运行，Flutter是如何实现的？| 极客时间",
        "link": "https://www.ershicimi.com/p/1320ac378693b34f3e16d99b17fb0dea",
        "date": "2021-03-08"
      },
      {
        "title": "腾讯前员工因违反竞业协议赔偿近百万；Flutter 2正式发布；PS5主机被破解，挖矿算力远超高端显",
        "link": "https://www.ershicimi.com/p/30e8237e03d5d321ee0bb1c9ab196cb9",
        "date": "2021-03-07"
      },
      {
        "title": "重磅！Flutter 2 来了！",
        "link": "https://www.ershicimi.com/p/c1c4915e92b6fbe44ba10ce434249989",
        "date": "2021-03-04"
      },
      {
        "title": "Deno 1.8 正式发布：附带完整的 ICU 支持；deno lsp 和导入映射均已稳定",
        "link": "https://www.ershicimi.com/p/a6b62bbcb7c6586c2c5031c80f15b8f0",
        "date": "2021-03-03"
      },
      {
        "title": "为什么要用 picture 标签代替 img 标签？",
        "link": "https://www.ershicimi.com/p/bb4e8b09847e1d97c14f80aac0490adc",
        "date": "2021-03-03"
      },
      {
        "title": "玩转可视化：这里有一些小技巧 | 活动推荐",
        "link": "https://www.ershicimi.com/p/9cd20066a0d94061a5c65415cecce0c4",
        "date": "2021-03-03"
      },
      {
        "title": "2021年Node.js开发人员学习路线图",
        "link": "https://www.ershicimi.com/p/26ac4d14019e4dc1a88e36e4b97dc8ee",
        "date": "2021-03-01"
      },
      {
        "title": "为什么说开发者指标是不可靠的？",
        "link": "https://www.ershicimi.com/p/b455355be1003bd2cd7ec643dc9897dd",
        "date": "2021-03-01"
      },
      {
        "title": "你每天都在使用的HTTP协议，到底是什么鬼？ | 活动推荐",
        "link": "https://www.ershicimi.com/p/7aca27fefd0e28c3fa0e825e404e1e4c",
        "date": "2021-03-01"
      }
    ]
  },
  {
    "rss": "https://front-rss.herokuapp.com/wechat/ershicimi/9457",
    "title": "前端迷",
    "link": "https://www.ershicimi.com/a/9457",
    "items": [
      {
        "title": "React+Ts+Node+MongoDB 构建 Todo App项目总结",
        "link": "https://www.ershicimi.com/p/599e80626ae227d3a388face93447042",
        "date": "2021-03-11"
      },
      {
        "title": "腾讯、华为2021前端技术岗发布+最新内部面试题",
        "link": "https://www.ershicimi.com/p/0e85e26848a6b56737b467525143d0a8",
        "date": "2021-03-10"
      },
      {
        "title": "聊聊 React 组件库的技术选型与设计",
        "link": "https://www.ershicimi.com/p/350881b759598304d68603b8132e8ebe",
        "date": "2021-03-09"
      },
      {
        "title": "Vue 和 React 大厂面试通关指南.pdf",
        "link": "https://www.ershicimi.com/p/115bae6604fd823db962ea9920a82cc2",
        "date": "2021-03-08"
      },
      {
        "title": "新兴前端框架 Svelte 从入门到原理",
        "link": "https://www.ershicimi.com/p/5fd1f2226b8befa7ca0b32b94494e56e",
        "date": "2021-03-07"
      },
      {
        "title": "推荐几个前端大佬，是真滴厉害！",
        "link": "https://www.ershicimi.com/p/53b34d9f78460e36255572b89de4598e",
        "date": "2021-03-06"
      },
      {
        "title": "Webpack5 新特性业务落地实战",
        "link": "https://www.ershicimi.com/p/bac670626de5a16a906fa5785ef35771",
        "date": "2021-03-05"
      },
      {
        "title": "美团到店餐饮急招前端，要求如下",
        "link": "https://www.ershicimi.com/p/36fc4853ccd30f3b6ce4c48db5be8ea4",
        "date": "2021-03-04"
      },
      {
        "title": "前端学到什么程度才能叫精通？",
        "link": "https://www.ershicimi.com/p/26d9168f1d04085ccfcaf2f48ed3bb2d",
        "date": "2021-03-03"
      },
      {
        "title": "前端拓展：如何开发一个 Chrome 插件？",
        "link": "https://www.ershicimi.com/p/e21959f7f8c8c34ceb31238d4fff0084",
        "date": "2021-03-02"
      },
      {
        "title": "《前端中文入门手册》.pdf",
        "link": "https://www.ershicimi.com/p/79f5cc8706999fa4d5813bcf26c0f85c",
        "date": "2021-03-01"
      },
      {
        "title": "React 表单源码阅读笔记",
        "link": "https://www.ershicimi.com/p/0f18396dff645b93ccc1357727a458ef",
        "date": "2021-02-28"
      },
      {
        "title": "Vue3diff算法原理和优化",
        "link": "https://www.ershicimi.com/p/5afc9993830acf1b0db659ccd05c76f8",
        "date": "2021-02-27"
      },
      {
        "title": "福利！3h后，删！",
        "link": "https://www.ershicimi.com/p/15ba903211a492241fd4dedd2af316e5",
        "date": "2021-02-27"
      },
      {
        "title": "随机送3本书，祝大家元宵节快乐。",
        "link": "https://www.ershicimi.com/p/81ad05c6c5d1e1f7c472b3ce64253185",
        "date": "2021-02-26"
      },
      {
        "title": "用canvas编辑你的图片",
        "link": "https://www.ershicimi.com/p/b77d97409c8f667fe53026482ce85bed",
        "date": "2021-02-25"
      },
      {
        "title": "自学前端的高效学习路线.avi",
        "link": "https://www.ershicimi.com/p/49b657b9628081fbcaf20d7edc12c4bd",
        "date": "2021-02-24"
      },
      {
        "title": "【小技巧】让你的 GitHub 秒变高大上！",
        "link": "https://www.ershicimi.com/p/f7bad73d0f55c439c1c2771d9345adb9",
        "date": "2021-02-23"
      },
      {
        "title": "webpack图解指南（模块化部分）",
        "link": "https://www.ershicimi.com/p/33a8c3e5216c85b2831c42459ddf6b3e",
        "date": "2021-02-20"
      },
      {
        "title": "从0搭建React开发环境",
        "link": "https://www.ershicimi.com/p/540141f8f6eaa2c07bd82782970e13da",
        "date": "2021-02-18"
      }
    ]
  },
  {
    "rss": "https://front-rss.herokuapp.com/wechat/ershicimi/9323",
    "title": "全栈前端精选",
    "link": "https://www.ershicimi.com/a/9323",
    "items": [
      {
        "title": "温故而知新，8张 Javascript 思维导图助你成长",
        "link": "https://www.ershicimi.com/p/942f275bb42690b6ccfa058f2c7ae3e8",
        "date": "2021-03-17"
      },
      {
        "title": "卧槽！VSCode 竟然可以找对象了！",
        "link": "https://www.ershicimi.com/p/7851cdcc75c29c4a8726932eeea93abd",
        "date": "2021-03-17"
      },
      {
        "title": "阿里面试官问“说一下从 url 输入到返回请求的过程”的难度就是不一样！",
        "link": "https://www.ershicimi.com/p/a3dc94113685eceeef15776172d1f8cb",
        "date": "2021-03-16"
      },
      {
        "title": "Flutter 2 来了！",
        "link": "https://www.ershicimi.com/p/bcc739f567b61cf883623079f6439f91",
        "date": "2021-03-15"
      },
      {
        "title": "你不知道的浏览器渲染原理",
        "link": "https://www.ershicimi.com/p/256db53e1130ad8bbf89b49547f47cb8",
        "date": "2021-03-14"
      },
      {
        "title": "奇思妙想 CSS 文字动画",
        "link": "https://www.ershicimi.com/p/a6d301b266223d57832c1165bbdaa43c",
        "date": "2021-03-14"
      },
      {
        "title": "前端也要懂编译：Babel 最全上手指南",
        "link": "https://www.ershicimi.com/p/2914447421b3926b496cddde919bc58f",
        "date": "2021-03-13"
      },
      {
        "title": "下一代前端构建工具 Vite （中英双语字幕）",
        "link": "https://www.ershicimi.com/p/28a9fee13aacb440f71cedf8ba5b4fed",
        "date": "2021-03-12"
      },
      {
        "title": "华为没有996? 不加班的955公司名单出炉！",
        "link": "https://www.ershicimi.com/p/5f1e34069d10d859fb312fb1fd7af278",
        "date": "2021-03-12"
      },
      {
        "title": "Vue 和 React 大厂面试通关指南.pdf",
        "link": "https://www.ershicimi.com/p/22c565625299296442ebdcba76f74fef",
        "date": "2021-03-11"
      },
      {
        "title": "Deno 将停用 TypeScript 的五个原因",
        "link": "https://www.ershicimi.com/p/1dc0f76e752240c19563b98f6bcbbffe",
        "date": "2021-03-11"
      },
      {
        "title": "高性能 JavaScript 引擎 V8 - 垃圾回收",
        "link": "https://www.ershicimi.com/p/a9609211bfdfc2c672d04aedb26c2917",
        "date": "2021-03-10"
      },
      {
        "title": "新兴前端框架 Svelte 从入门到原理",
        "link": "https://www.ershicimi.com/p/ae14a5836820218571a7982e2d1dbc04",
        "date": "2021-03-09"
      },
      {
        "title": "字节跳动2021前端技术岗发布+最新内部面试题",
        "link": "https://www.ershicimi.com/p/51e062c6960c3e3dd6e9646a053cd727",
        "date": "2021-03-08"
      },
      {
        "title": "使用 Webpack5 从 0 搭建 React开发环境(详细篇)",
        "link": "https://www.ershicimi.com/p/c79b508b8d9c36845d9968bc44da75e6",
        "date": "2021-03-08"
      },
      {
        "title": "2021 写博客指南【万字长文】",
        "link": "https://www.ershicimi.com/p/3cdee446cb426b6235792f5fd3c35c38",
        "date": "2021-03-07"
      },
      {
        "title": "【文末抽奖送书】手把手教你如何制作可视化大屏！",
        "link": "https://www.ershicimi.com/p/7b4c85127b4460967a229cd4a1efcc92",
        "date": "2021-03-06"
      },
      {
        "title": "前端优秀实践不完全指南【追求极致用户体验】",
        "link": "https://www.ershicimi.com/p/e7e13a6d7b977322de79fa73173c1ba2",
        "date": "2021-03-05"
      },
      {
        "title": "谈一下React 的Fiber架构和Hooks",
        "link": "https://www.ershicimi.com/p/cb0b4aa88d728e37153ddfb9874cb514",
        "date": "2021-03-04"
      },
      {
        "title": "5个不常提及的HTML技巧",
        "link": "https://www.ershicimi.com/p/b1d9187a31478c643739cbca5a53ea8f",
        "date": "2021-03-04"
      }
    ]
  },
  {
    "rss": "https://front-rss.herokuapp.com/wechat/ershicimi/10195",
    "title": "政采云前端团队",
    "link": "https://www.ershicimi.com/a/10195",
    "items": []
  },
  {
    "rss": "https://front-rss.herokuapp.com/wechat/ershicimi/8801",
    "title": "前端宇宙",
    "link": "https://www.ershicimi.com/a/8801",
    "items": []
  },
  {
    "rss": "https://front-rss.herokuapp.com/wechat/ershicimi/10641",
    "title": "前端瓶子君",
    "items": [],
    "link": "https://www.ershicimi.com/a/10641"
  },
  {
    "rss": "https://front-rss.herokuapp.com/wechat/ershicimi/10108",
    "title": "程序员成长指北",
    "link": "https://www.ershicimi.com/a/10108",
    "items": []
  },
  {
    "rss": "https://front-rss.herokuapp.com/wechat/ershicimi/10545",
    "title": "Nodejs技术栈",
    "link": "https://www.ershicimi.com/a/10545",
    "items": []
  },
  {
    "rss": "https://www.zhangxinxu.com/wordpress/feed/",
    "title": "张鑫旭-鑫空间-鑫生活",
    "link": "https://www.zhangxinxu.com/wordpress",
    "items": [
      {
        "title": "CSS line-height-step属性简介",
        "link": "https://www.zhangxinxu.com/wordpress/2021/03/css-line-height-step/",
        "date": "2021-03-14"
      },
      {
        "title": "使用CSS text-combine-upright实现字符的横向合并",
        "link": "https://www.zhangxinxu.com/wordpress/2021/02/css-text-combine-upright/",
        "date": "2021-02-18"
      },
      {
        "title": "CSS line-break属性与中文标点换行",
        "link": "https://www.zhangxinxu.com/wordpress/2021/02/css-line-break/",
        "date": "2021-02-18"
      },
      {
        "title": "Chrome 88已经支持aspect-ratio属性了，学起来",
        "link": "https://www.zhangxinxu.com/wordpress/2021/02/css-aspect-ratio/",
        "date": "2021-02-17"
      },
      {
        "title": "好消息，CSS text-underline-offset可以用起来了",
        "link": "https://www.zhangxinxu.com/wordpress/2021/02/css-text-underline-offset/",
        "date": "2021-02-17"
      },
      {
        "title": "CSS ::marker伪元素简介",
        "link": "https://www.zhangxinxu.com/wordpress/2021/02/css-marker-pseudo-element/",
        "date": "2021-02-16"
      },
      {
        "title": "盘点HTML字符串转DOM的各种方法及细节",
        "link": "https://www.zhangxinxu.com/wordpress/2021/02/html-string-dom/",
        "date": "2021-02-16"
      },
      {
        "title": "如何使用JS检测用户是否缩放了页面？",
        "link": "https://www.zhangxinxu.com/wordpress/2021/02/js-if-page-zoom/",
        "date": "2021-02-15"
      },
      {
        "title": "直线等图形从中间穿过元素或文字的CSS实现",
        "link": "https://www.zhangxinxu.com/wordpress/2021/02/css-3d-through/",
        "date": "2021-02-14"
      },
      {
        "title": "了解CSS revert全局关键字",
        "link": "https://www.zhangxinxu.com/wordpress/2021/02/css-revert/",
        "date": "2021-02-14"
      }
    ]
  },
  {
    "rss": "http://www.ruanyifeng.com/blog/atom.xml",
    "title": "阮一峰的网络日志",
    "link": "http://www.ruanyifeng.com/blog/",
    "items": [
      {
        "title": "科技爱好者周刊（第 149 期）：新能源汽车，谁会是赢家？",
        "link": "http://www.ruanyifeng.com/blog/2021/03/weekly-issue-149.html",
        "date": "2021-03-12"
      },
      {
        "title": "科技爱好者周刊（第 148 期）：微增长时代",
        "link": "http://www.ruanyifeng.com/blog/2021/03/weekly-issue-148.html",
        "date": "2021-03-05"
      },
      {
        "title": "科技爱好者周刊（第 147 期）：寻找你愿意忍受的痛苦",
        "link": "http://www.ruanyifeng.com/blog/2021/02/weekly-issue-147.html",
        "date": "2021-02-26"
      }
    ]
  },
  {
    "rss": "http://jdc.jd.com/feed",
    "title": "京东设计中心",
    "items": [],
    "link": "https://jdc.jd.com"
  },
  {
    "rss": "https://aotu.io/atom.xml",
    "title": "凹凸实验室",
    "link": "/atom.xml",
    "items": []
  },
  {
    "rss": "https://front-rss.herokuapp.com/wechat/ershicimi/6210",
    "title": "奇舞周刊",
    "link": "https://www.ershicimi.com/a/6210",
    "items": []
  },
  {
    "rss": "https://front-rss.herokuapp.com/wechat/ershicimi/5762",
    "title": "前端日刊",
    "link": "https://www.ershicimi.com/a/5762",
    "items": []
  },
  {
    "rss": "https://front-rss.herokuapp.com/wechat/ershicimi/10548",
    "title": "前端e进阶",
    "link": "https://www.ershicimi.com/a/10548",
    "items": []
  },
  {
    "rss": "https://front-rss.herokuapp.com/wechat/ershicimi/6304",
    "title": "互联网架构师",
    "link": "https://www.ershicimi.com/a/6304",
    "items": []
  },
  {
    "rss": "https://front-rss.herokuapp.com/wechat/ershicimi/89",
    "title": "InfoQ",
    "link": "https://www.ershicimi.com/a/89",
    "items": []
  },
  {
    "rss": "https://front-rss.herokuapp.com/wechat/ershicimi/893",
    "title": "JavaScript",
    "link": "https://www.ershicimi.com/a/893",
    "items": []
  },
  {
    "rss": "https://front-rss.herokuapp.com/juejin/category/frontend",
    "title": "掘金前端",
    "link": "https://juejin.im/welcome/frontend",
    "items": []
  },
  {
    "rss": "https://front-rss.herokuapp.com/jskou/0",
    "title": "前端艺术家&&飞冰早报",
    "link": "http://fe.jskou.com/",
    "items": [
      {
        "title": "【canvas】动画原理の万有引力定律",
        "link": "https://juejin.im/post/5e213c83f265da3e006b3fc0",
        "date": "2020-01-18"
      },
      {
        "title": "JavaScript️可视化：事件循环",
        "link": "https://juejin.im/post/5e218b8af265da3e121824eb",
        "date": "2020-01-18"
      },
      {
        "title": "JavaScript的强语言之路—另类的JSON序列化与反序列化",
        "link": "https://juejin.im/post/5e1f23d76fb9a02fec664828",
        "date": "2020-01-18"
      },
      {
        "title": "自动化部署的一小步，前端搬砖的一大步",
        "link": "https://juejin.im/post/5e206168f265da3e2b2d7560",
        "date": "2020-01-18"
      },
      {
        "title": "让App热更多个RN项目的解决方案",
        "link": "https://juejin.im/post/5df6ecec51882512533a876b",
        "date": "2019-12-18"
      },
      {
        "title": "Vue Testing Crash Course",
        "link": "https://dev.to/blacksonic/vue-testing-crash-course-59kl",
        "date": "2019-12-18"
      },
      {
        "title": "淘宝技术架构演进",
        "link": "https://mp.weixin.qq.com/s/FXo9eVPNLKAPDjLDX6pvwQ",
        "date": "2019-12-16"
      },
      {
        "title": "Webpack打包改造--插入自定义内容",
        "link": "https://juejin.im/post/5df4a220f265da33de3a74b0",
        "date": "2019-12-16"
      },
      {
        "title": "b站全灰，但我一下把它弄回来了——css 滤镜",
        "link": "https://juejin.im/post/5df3a049f265da33f8652882",
        "date": "2019-12-16"
      },
      {
        "title": "以中国传统的孔子和老子的思想来分析忍者代码",
        "link": "https://juejin.im/post/5df06050e51d4557f26e52e3",
        "date": "2019-12-16"
      },
      {
        "title": "「从模板消息改版订阅消息」小程序推送",
        "link": "https://juejin.im/post/5df03c3551882512243f9292",
        "date": "2019-12-12"
      },
      {
        "title": "Flexbox：使用 Auto Margin 对齐",
        "link": "https://juejin.im/post/5dedb2fd6fb9a016323d7202",
        "date": "2019-12-12"
      },
      {
        "title": "9102 年，蚂蚁金服前端是怎么写图表的?",
        "link": "https://zhuanlan.zhihu.com/p/93963320",
        "date": "2019-12-09"
      },
      {
        "title": "图表制作可以很简单 - 图表魔方 ChartCube",
        "link": "https://zhuanlan.zhihu.com/p/94269648",
        "date": "2019-12-09"
      },
      {
        "title": "微前端的核心价值",
        "link": "https://zhuanlan.zhihu.com/p/95085796",
        "date": "2019-12-06"
      },
      {
        "title": "解密国内BAT等大厂前端技术体系-美团点评之上篇（长文建议收藏）",
        "link": "https://juejin.im/post/5de6474bf265da33af512598",
        "date": "2019-12-06"
      },
      {
        "title": "你可能不知道的 JavaScript 代码 Chrome 调试方法",
        "link": "https://zh.javascript.info/debugging-chrome",
        "date": "2019-12-06"
      },
      {
        "title": "crypto 前后端加解密简单了解",
        "link": "https://juejin.im/post/5de70298f265da33b12e8221",
        "date": "2019-12-05"
      },
      {
        "title": "How to choose a JavaScript code editor",
        "link": "https://www.freecodecamp.org/news/how-to-choose-a-javascript-code-editor/",
        "date": "2019-12-05"
      },
      {
        "title": "京喜首页（微信购物入口）跨端开发与优化实践",
        "link": "https://juejin.im/post/5de66e916fb9a015fd699b46",
        "date": "2019-12-05"
      },
      {
        "title": "Node.js项目TypeScript改造指南",
        "link": "https://juejin.im/post/5de4867f51882573135415dd",
        "date": "2019-12-04"
      },
      {
        "title": "EHTML: HTML Framework that allows you write no JavaScript code at all.",
        "link": "https://guseyn.com/posts/frontend-development-can-and-should-be-simple?v=1.0.173",
        "date": "2019-12-04"
      },
      {
        "title": "一起console.log()引发的血案",
        "link": "https://juejin.im/post/5de3ed6e6fb9a0717f5af175",
        "date": "2019-12-03"
      },
      {
        "title": "从3 个方面增加代码可读性和可维护性",
        "link": "https://juejin.im/post/5de3b7c4e51d45777714f34f",
        "date": "2019-12-03"
      },
      {
        "title": "api请求时长与请求数据类型的设计",
        "link": "https://juejin.im/post/5de28460e51d4532f87096e2",
        "date": "2019-12-02"
      },
      {
        "title": "（译）JavaScript的工作原理：事件循环和异步编程的兴起 + 5 种 async/await 更好的编码方式",
        "link": "https://juejin.im/post/5ddf3dce6fb9a071a254721b",
        "date": "2019-12-02"
      },
      {
        "title": "JavaScript 是怎么工作的：内存管理及怎么处理四种常见的内存泄露",
        "link": "https://juejin.im/post/5de08bd26fb9a071bb7cab56",
        "date": "2019-12-02"
      },
      {
        "title": "没有用过这些插件，别说你在用vscode",
        "link": "https://juejin.im/post/5dc97976e51d45066f3a7b6b",
        "date": "2019-11-13"
      },
      {
        "title": "云凤蝶可视化搭建的推导与实现",
        "link": "https://zhuanlan.zhihu.com/p/90746742",
        "date": "2019-11-13"
      },
      {
        "title": "动画：面试官问我如何在 1 亿数据中快速查找某一整数？",
        "link": "https://juejin.im/post/5dc786026fb9a04a7847f56a",
        "date": "2019-11-13"
      }
    ]
  },
  {
    "rss": "https://front-rss.herokuapp.com/docschina/jsweekly",
    "title": "印记中文周刊",
    "link": "https://weekly.docschina.org",
    "items": []
  },
  {
    "rss": "https://front-rss.herokuapp.com/wechat/ershicimi/10647",
    "title": "编程之上",
    "link": "https://www.ershicimi.com/a/10647",
    "items": []
  },
  {
    "rss": "https://front-rss.herokuapp.com/wechat/ershicimi/198",
    "title": "知乎日报",
    "link": "https://www.ershicimi.com/a/198",
    "items": []
  },
  {
    "rss": "https://front-rss.herokuapp.com/v2ex/topics/latest",
    "title": "V2EX",
    "link": "https://www.v2ex.com/",
    "items": [
      {
        "title": "学了 6 年计算机，我想问问大家什么是 B 减树？",
        "link": "https://www.v2ex.com/t/763009",
        "date": "2021-03-18"
      },
      {
        "title": "假如你遇到一个顶级的产品经理，邀请你一起创业，你是否愿意赌一把？",
        "link": "https://www.v2ex.com/t/763008",
        "date": "2021-03-18"
      },
      {
        "title": "可以使用 GitLab 进行项目管理吗？",
        "link": "https://www.v2ex.com/t/763006",
        "date": "2021-03-18"
      },
      {
        "title": "第一个 Flutter 项目终于上架 App Store 了，终于有资格聊聊 Flutter 了。",
        "link": "https://www.v2ex.com/t/763005",
        "date": "2021-03-18"
      },
      {
        "title": "手机在灯光下拍摄闪烁问题",
        "link": "https://www.v2ex.com/t/763004",
        "date": "2021-03-18"
      },
      {
        "title": "拼夕夕上的书 真便宜呀~",
        "link": "https://www.v2ex.com/t/763001",
        "date": "2021-03-18"
      },
      {
        "title": "Laravel Octane 是什么，以及为什么它可以把传统 Laravel 应用性能提升十倍？",
        "link": "https://www.v2ex.com/t/763000",
        "date": "2021-03-18"
      },
      {
        "title": "请教一下大佬们关于应届生找工作的问题",
        "link": "https://www.v2ex.com/t/762998",
        "date": "2021-03-18"
      },
      {
        "title": "华为 OD 怎么样",
        "link": "https://www.v2ex.com/t/762996",
        "date": "2021-03-18"
      },
      {
        "title": "win10 更新最大感受是 bug",
        "link": "https://www.v2ex.com/t/762995",
        "date": "2021-03-18"
      },
      {
        "title": "一个极简风格的音乐网站，试图减少你来回切换音乐软件的烦恼~",
        "link": "https://www.v2ex.com/t/762993",
        "date": "2021-03-18"
      },
      {
        "title": "工作选择（是否换工作）",
        "link": "https://www.v2ex.com/t/762992",
        "date": "2021-03-18"
      },
      {
        "title": "苹果屏幕密码输错了 6 次, 提示要刷机了，突然又把密码想起来了，怎么保留原来里面的数据",
        "link": "https://www.v2ex.com/t/762991",
        "date": "2021-03-18"
      },
      {
        "title": "Mac 下 Firefox 的 4K 视频解码问题",
        "link": "https://www.v2ex.com/t/762989",
        "date": "2021-03-18"
      },
      {
        "title": "嘴里溃疡长在了奇怪的地方，求各位经验",
        "link": "https://www.v2ex.com/t/762988",
        "date": "2021-03-18"
      },
      {
        "title": "各位做 BI 项目都是怎么选型的？",
        "link": "https://www.v2ex.com/t/762987",
        "date": "2021-03-18"
      },
      {
        "title": "g304 买了不到一个月左键就开始有问题了",
        "link": "https://www.v2ex.com/t/762986",
        "date": "2021-03-18"
      },
      {
        "title": "33 岁老程序员的犹豫： 继续做几个人的团队管理（偏业务方向），还是选择新业务（机器学习）技术开发方向？",
        "link": "https://www.v2ex.com/t/762985",
        "date": "2021-03-18"
      },
      {
        "title": "寻扩充的“以鼠标位置为中心的滑轮放大功能”代码",
        "link": "https://www.v2ex.com/t/762984",
        "date": "2021-03-18"
      },
      {
        "title": "[干货] 微软内部面试题",
        "link": "https://www.v2ex.com/t/762983",
        "date": "2021-03-18"
      },
      {
        "title": "适合 esxi 的工控机",
        "link": "https://www.v2ex.com/t/762982",
        "date": "2021-03-18"
      },
      {
        "title": "鉴于每天需要收集整理大量的资讯内容，请问有什么好的内容整理工具或者程序可用吗？",
        "link": "https://www.v2ex.com/t/762981",
        "date": "2021-03-18"
      },
      {
        "title": "为什么不自己管理公钥密钥，而要用第三方的钱包软件？",
        "link": "https://www.v2ex.com/t/762980",
        "date": "2021-03-18"
      },
      {
        "title": "关于拉格朗日乘数法的一个问题 ？（无关考试，就是想搞懂）",
        "link": "https://www.v2ex.com/t/762979",
        "date": "2021-03-18"
      },
      {
        "title": "蓝牙耳机在通话时为什么会音质骤降出现电流声？",
        "link": "https://www.v2ex.com/t/762978",
        "date": "2021-03-18"
      },
      {
        "title": "视频：谷歌原生 Android 12 DP2 有哪些更新和变化",
        "link": "https://www.v2ex.com/t/762977",
        "date": "2021-03-18"
      },
      {
        "title": "有什么代餐粉或代餐饼推荐？",
        "link": "https://www.v2ex.com/t/762976",
        "date": "2021-03-18"
      },
      {
        "title": "社保有人断过吗，应该怎么补上啊",
        "link": "https://www.v2ex.com/t/762975",
        "date": "2021-03-18"
      },
      {
        "title": "[苹果限免应用推荐]3/18⏰|App Store",
        "link": "https://www.v2ex.com/t/762974",
        "date": "2021-03-18"
      },
      {
        "title": "ToDesk Beta 2.2 远程控制软件",
        "link": "https://www.v2ex.com/t/762973",
        "date": "2021-03-18"
      },
      {
        "title": "[百度] 百度内推激励给够！",
        "link": "https://www.v2ex.com/t/762972",
        "date": "2021-03-18"
      },
      {
        "title": "求助，站点无法访问",
        "link": "https://www.v2ex.com/t/762970",
        "date": "2021-03-18"
      },
      {
        "title": "（假如）你是领导，你喜欢把内心想法都说出来的员工吗？",
        "link": "https://www.v2ex.com/t/762969",
        "date": "2021-03-18"
      },
      {
        "title": "ebay 封号 6 分钟速通......",
        "link": "https://www.v2ex.com/t/762968",
        "date": "2021-03-18"
      },
      {
        "title": "👋有没有这样一个移动端书签整理 app",
        "link": "https://www.v2ex.com/t/762966",
        "date": "2021-03-18"
      },
      {
        "title": "Python 使用 pyqtgraph 绘制大量文本标记 速度问题",
        "link": "https://www.v2ex.com/t/762965",
        "date": "2021-03-18"
      },
      {
        "title": "今天收到一份职场的意外惊喜",
        "link": "https://www.v2ex.com/t/762964",
        "date": "2021-03-18"
      },
      {
        "title": "浏览器输入网址打开 和 打开后 ctlr+F5 清除缓存的刷新 为什么打开时间差别很大",
        "link": "https://www.v2ex.com/t/762963",
        "date": "2021-03-18"
      },
      {
        "title": "[Shopee 虾皮｜金三银四｜乘风破浪！] [Leader/后端/前端/数据/测试/产品] 大量 hc，高速发展中，快来瞅瞅",
        "link": "https://www.v2ex.com/t/762962",
        "date": "2021-03-18"
      },
      {
        "title": "广东省前端内推群，一起来呀~~",
        "link": "https://www.v2ex.com/t/762961",
        "date": "2021-03-18"
      },
      {
        "title": "有个带公网 1G 联通宽带，有什么用，除了野鸡 CDN",
        "link": "https://www.v2ex.com/t/762960",
        "date": "2021-03-18"
      }
    ]
  },
  {
    "rss": "https://front-rss.herokuapp.com/blogread/newest",
    "title": "技术头条",
    "link": "http://blogread.cn/news/newest.php",
    "items": []
  },
  {
    "rss": "https://front-rss.herokuapp.com/toutiao/today",
    "title": "开发者头条",
    "link": "https://toutiao.io",
    "items": [
      {
        "title": "如何写出高质量的技术文章？",
        "link": "https://toutiao.io/k/ozl31qb",
        "date": "2021-03-18"
      },
      {
        "title": "工具 | 阿里妈妈出品的，简单易上手，可读性强的 AST 处理工具",
        "link": "https://toutiao.io/k/g620cqe",
        "date": "2021-03-18"
      },
      {
        "title": "Synchronized 升级到重量级锁之后就下不来了？你错了",
        "link": "https://toutiao.io/k/puahuvi",
        "date": "2021-03-18"
      },
      {
        "title": "如何将 Canvas 绘制过程转为视频",
        "link": "https://toutiao.io/k/eg2ql65",
        "date": "2021-03-18"
      },
      {
        "title": "低代码、无代码、零代码",
        "link": "https://toutiao.io/k/x603bub",
        "date": "2021-03-18"
      },
      {
        "title": "几个你不知道的 dubbo 注册中心细节",
        "link": "https://toutiao.io/k/qmh5nuk",
        "date": "2021-03-18"
      },
      {
        "title": "为什么 Kubernetes 要替换 Docker",
        "link": "https://toutiao.io/k/uhmrz9z",
        "date": "2021-03-18"
      },
      {
        "title": "程序员，45 岁",
        "link": "https://toutiao.io/k/ox7q9bl",
        "date": "2021-03-18"
      },
      {
        "title": "RPC 接口将所有输入输出封装成类是合理设计吗",
        "link": "https://toutiao.io/k/9va5i4e",
        "date": "2021-03-18"
      },
      {
        "title": "Android 极简跳转页面工具",
        "link": "https://toutiao.io/k/wvnv50m",
        "date": "2021-03-18"
      },
      {
        "title": "数仓主题域、主题、业务域之间有什么的关系",
        "link": "https://toutiao.io/k/432ivfx",
        "date": "2021-03-18"
      },
      {
        "title": "基本的数论类算法（埃拉托斯特尼筛法、快速素数筛法 ）",
        "link": "https://toutiao.io/k/yg7tg91",
        "date": "2021-03-18"
      },
      {
        "title": "Arthas 3.5.0 版本发布，支持反编译打印行号和统一鉴权",
        "link": "https://toutiao.io/k/zdov9il",
        "date": "2021-03-18"
      },
      {
        "title": "梆梆 App 加固产品方案浅析",
        "link": "https://toutiao.io/k/gs3z7a5",
        "date": "2021-03-18"
      },
      {
        "title": "《深度学习推荐系统》笔记（二）：立于道，工于技",
        "link": "https://toutiao.io/k/ywivvnc",
        "date": "2021-03-18"
      },
      {
        "title": "Docker 实战：基础操作",
        "link": "https://toutiao.io/k/7rr7vjq",
        "date": "2021-03-18"
      },
      {
        "title": "Serverless Wordpress 系列建站教程（四）",
        "link": "https://toutiao.io/k/njht4il",
        "date": "2021-03-18"
      },
      {
        "title": "介绍一个本地 DynamoDB 图形界面应用：dynamodb-admin",
        "link": "https://toutiao.io/k/pshktgy",
        "date": "2021-03-18"
      },
      {
        "title": "二进制手表",
        "link": "https://toutiao.io/k/0s28r5p",
        "date": "2021-03-18"
      },
      {
        "title": "今日头条 ANR 优化实践系列：设计原理及影响因素",
        "link": "https://toutiao.io/k/9b0suhy",
        "date": "2021-03-18"
      },
      {
        "title": "[推荐] Tomcat 性能调优应该注意什么？",
        "link": "https://toutiao.io/k/kldrkzc",
        "date": "2021-03-18"
      },
      {
        "title": "[推荐] 职场：3 天准备 5 天面试，跳槽完成",
        "link": "https://toutiao.io/k/1d2mnjh",
        "date": "2021-03-18"
      },
      {
        "title": "[推荐] 内存管理设计精要",
        "link": "https://toutiao.io/k/4f2u3c5",
        "date": "2021-03-18"
      },
      {
        "title": "[推荐] 谈谈 Git 存储原理及相关实现",
        "link": "https://toutiao.io/k/mzszqf0",
        "date": "2021-03-18"
      },
      {
        "title": "[推荐] MySQL 索引从基础到原理，看这一篇就够了",
        "link": "https://toutiao.io/k/hueiax0",
        "date": "2021-03-18"
      },
      {
        "title": "[推荐] 有赞 BI 平台设计及实现",
        "link": "https://toutiao.io/k/a595tmo",
        "date": "2021-03-18"
      },
      {
        "title": "[推荐] [译] 构建微服务的十大 Go 框架/库",
        "link": "https://toutiao.io/k/44rsmt3",
        "date": "2021-03-18"
      },
      {
        "title": "[推荐] 从技术专家到技术管理，我对管理的思考",
        "link": "https://toutiao.io/k/r5kgujp",
        "date": "2021-03-18"
      },
      {
        "title": "[推荐] 国内有哪些顶级技术团队的博客值得推荐？",
        "link": "https://toutiao.io/k/j7v5pee",
        "date": "2021-03-18"
      },
      {
        "title": "[推荐] 去哪里找 Java 练手项目？",
        "link": "https://toutiao.io/k/qh7wgrx",
        "date": "2021-03-18"
      },
      {
        "title": "[推荐] 21 大软件架构特点的全面解析",
        "link": "https://toutiao.io/k/2n0entj",
        "date": "2021-03-18"
      },
      {
        "title": "[推荐] 聊聊 IT 技术人的知识体系",
        "link": "https://toutiao.io/k/vmimc5g",
        "date": "2021-03-18"
      },
      {
        "title": "[推荐] Golang 性能诊断看这篇就够了",
        "link": "https://toutiao.io/k/3loin1u",
        "date": "2021-03-18"
      },
      {
        "title": "[推荐] 万字长文聊缓存（下）：应用级缓存",
        "link": "https://toutiao.io/k/c1uc4c2",
        "date": "2021-03-18"
      },
      {
        "title": "[推荐] 快手超大规模集群调度优化实践",
        "link": "https://toutiao.io/k/671eano",
        "date": "2021-03-18"
      }
    ]
  },
  {
    "rss": "https://sec.thief.one/atom.xml",
    "title": "安全热点",
    "link": "https://sec.thief.one/",
    "items": [
      {
        "title": "16美元就可以打包带走所有短信,你的手机号还安全吗?",
        "link": "https://sec.thief.one/article_content?a_id=a5132bfc3fc98f65d368b9359804cd4f",
        "date": "2021-03-18"
      },
      {
        "title": "阿里安全今年首次开放风控策略类校招岗",
        "link": "https://sec.thief.one/article_content?a_id=909d1105a156f11827ca2624b0bdd486",
        "date": "2021-03-18"
      },
      {
        "title": "揭秘手游外挂:基于内存蜜罐的内存修改挂分析技术",
        "link": "https://sec.thief.one/article_content?a_id=bb16e27d3ffc7e816c4d752a92e291b9",
        "date": "2021-03-18"
      },
      {
        "title": "代码审计难?掌握这个学习思路,稳赢!",
        "link": "https://sec.thief.one/article_content?a_id=e0d427918a8e2ac0be078c7b6bcfeb6f",
        "date": "2021-03-18"
      },
      {
        "title": "明天见!",
        "link": "https://sec.thief.one/article_content?a_id=eef77bcecca844afe1d55314d0a64d57",
        "date": "2021-03-18"
      },
      {
        "title": "【漏洞通告】Apache Solr任意文件读取与SSRF漏洞",
        "link": "https://sec.thief.one/article_content?a_id=8c6c940b9da0473783011bb0c3c32c29",
        "date": "2021-03-18"
      },
      {
        "title": "你为什么入党?",
        "link": "https://sec.thief.one/article_content?a_id=30583d8eea5c66419ac0bb6911f0e8f8",
        "date": "2021-03-18"
      },
      {
        "title": "蓝队防守必须排查的17个内网安全漏洞与解决方案",
        "link": "https://sec.thief.one/article_content?a_id=c23ff61525a158f637880406c87b2f26",
        "date": "2021-03-18"
      },
      {
        "title": "百度安全重新定义Fuzzing 技术",
        "link": "https://sec.thief.one/article_content?a_id=0cc7efc5776fc780f3bf95a3d5c8f476",
        "date": "2021-03-18"
      },
      {
        "title": "美图购买更多比特币和以太,持有加密货币总价值达9000万美元",
        "link": "https://sec.thief.one/article_content?a_id=dcbe760ce16a3d7223d4217bbc3fccc1",
        "date": "2021-03-18"
      },
      {
        "title": "​315前夕,无辜90后女孩成了桃色新闻的主角",
        "link": "https://sec.thief.one/article_content?a_id=1da6181ea07e0bdbb709502e0a8390d4",
        "date": "2021-03-18"
      },
      {
        "title": "【风险提示】天融信关于GitLab远程代码执行漏洞风险提示",
        "link": "https://sec.thief.one/article_content?a_id=75acec374fda9831dd9e0cfd57f8228d",
        "date": "2021-03-18"
      },
      {
        "title": "【漏洞通告】GitLab 远程代码执行漏洞",
        "link": "https://sec.thief.one/article_content?a_id=13f9daaf3f8c17ea1a3b1271e436e106",
        "date": "2021-03-18"
      },
      {
        "title": "【安全风险通告】奇安信研究员发现并首发分析,产品线已支持防护,...",
        "link": "https://sec.thief.one/article_content?a_id=94a497437d74c1e21536b3a79ddf1115",
        "date": "2021-03-18"
      },
      {
        "title": "3月18日贵币GUIBI早内参-Filecoin将于4月减产,灰度新推出FIL等五种...",
        "link": "https://sec.thief.one/article_content?a_id=94663bba3404c3d7ad2e959042d6cf9f",
        "date": "2021-03-18"
      },
      {
        "title": "Technomous勒索瞄准VMware vSphere,虚拟化平台如何保障数据安全...",
        "link": "https://sec.thief.one/article_content?a_id=e779a41d975e6ac3bb861253e2184d1f",
        "date": "2021-03-18"
      },
      {
        "title": "调查:API安全成为威胁新趋势",
        "link": "https://sec.thief.one/article_content?a_id=acbd07d0f4454dae3a805ada2a2c29a7",
        "date": "2021-03-18"
      },
      {
        "title": "中大型企业工作负载漏洞管理最佳实践",
        "link": "https://sec.thief.one/article_content?a_id=2ef761fe0bdb86d347ec2bfa510f20b6",
        "date": "2021-03-18"
      },
      {
        "title": "「目极千里 · 洞见安全」安全技术沙龙来了!",
        "link": "https://sec.thief.one/article_content?a_id=4136a960e9b15ac5eab33ea02ee7a087",
        "date": "2021-03-18"
      },
      {
        "title": "驱动安全建设的三架马车",
        "link": "https://sec.thief.one/article_content?a_id=f051cde960aa26e135c8a81e30a682bc",
        "date": "2021-03-18"
      },
      {
        "title": "国家互联网信息办公室、公安部加强对语音社交软件和涉深度伪造技术...",
        "link": "https://sec.thief.one/article_content?a_id=d953cb102e597ceff02bf6572bd3aa3c",
        "date": "2021-03-18"
      },
      {
        "title": "2020失业将近1年,我赚了37万",
        "link": "https://sec.thief.one/article_content?a_id=5d6b9b409e75e70b3b8a10d68c013f06",
        "date": "2021-03-18"
      },
      {
        "title": "智利银行监管机构在Microsoft Exchange遭到黑客攻击后共享入侵IOC",
        "link": "https://sec.thief.one/article_content?a_id=6e1c0dd00598ce01b68762f376d393f7",
        "date": "2021-03-18"
      },
      {
        "title": "“猫池”藏“猫腻” “黑科技”成“帮凶”?",
        "link": "https://sec.thief.one/article_content?a_id=3fd625ea9dd1c8b01893ada7f8045462",
        "date": "2021-03-18"
      },
      {
        "title": "数据安全:国防部卫生系统存档COVID-19疫苗接种数据",
        "link": "https://sec.thief.one/article_content?a_id=2ef3ca65b5ac94030333694a67309a33",
        "date": "2021-03-18"
      },
      {
        "title": "国有资本持续入局,长扬科技完成D轮近2亿元战略融资",
        "link": "https://sec.thief.one/article_content?a_id=021d742b771369bfd8bd3801ff049839",
        "date": "2021-03-18"
      },
      {
        "title": "【视频】| Python:路径讲解(相对和绝对)",
        "link": "https://sec.thief.one/article_content?a_id=fb1b61447015a52ddb45d0e87ff04759",
        "date": "2021-03-18"
      },
      {
        "title": "手把手教你玩转macOS CrackMe破解五步走",
        "link": "https://sec.thief.one/article_content?a_id=1bcfd2fbeebf278937fa867037389d06",
        "date": "2021-03-18"
      },
      {
        "title": "15万摄像头遭入侵,特斯拉上海仓库也中枪,只因管理员密码就发在网...",
        "link": "https://sec.thief.one/article_content?a_id=bf151bcc180b9729438fa4b39f6d93e5",
        "date": "2021-03-18"
      },
      {
        "title": "为程序员和新手准备的 8 大 Python 工具",
        "link": "https://sec.thief.one/article_content?a_id=ad43edbd9be234f471a07d6010e6a558",
        "date": "2021-03-18"
      },
      {
        "title": "漫画:为什么程序猿 996 会猝死,而企业家 007 却不会?",
        "link": "https://sec.thief.one/article_content?a_id=abb73e460d007cb404ad2526e84c857e",
        "date": "2021-03-18"
      },
      {
        "title": "把脉定向 习近平解题“京津冀一体化”",
        "link": "https://sec.thief.one/article_content?a_id=3becad51863e1a76f686da562bf76bc8",
        "date": "2021-03-18"
      },
      {
        "title": "侧信道与故障注入攻击小结",
        "link": "https://sec.thief.one/article_content?a_id=936bd04c3b5ad41c6cfc55c72159eee5",
        "date": "2021-03-18"
      },
      {
        "title": "金三银四挖洞季 丨 TSRC专项众测正式启动!",
        "link": "https://sec.thief.one/article_content?a_id=7a78062643e934847710cb16fc716c63",
        "date": "2021-03-18"
      },
      {
        "title": "网安杂谈收藏夹2021.3.18",
        "link": "https://sec.thief.one/article_content?a_id=0ebb9243af2cfe135e4591f2079f1f60",
        "date": "2021-03-18"
      },
      {
        "title": "银保监会发布:关于防范短信钓鱼诈骗的风险提示",
        "link": "https://sec.thief.one/article_content?a_id=1d0829850636e98cdf60e71b7811e49b",
        "date": "2021-03-18"
      },
      {
        "title": "西安邮电大学网络空间安全学院人才招聘",
        "link": "https://sec.thief.one/article_content?a_id=9c372165aaebed9fb8a595e24b25fe8f",
        "date": "2021-03-17"
      },
      {
        "title": "美国情报机构称俄罗斯和伊朗参与干预大选而非中国",
        "link": "https://sec.thief.one/article_content?a_id=ce885ee366ef25a1ff6554f123d1bb72",
        "date": "2021-03-17"
      },
      {
        "title": "【安全圈】主流加密通信应用Signal被封杀",
        "link": "https://sec.thief.one/article_content?a_id=c697039212880dbc0a8a0208939a134e",
        "date": "2021-03-17"
      },
      {
        "title": "每日攻防资讯简报[Mar.17th]",
        "link": "https://sec.thief.one/article_content?a_id=93321491c3c40af5674b4b458bd0e3fa",
        "date": "2021-03-17"
      },
      {
        "title": "滴滴面试官:说说你的能力模型为什么值 50W",
        "link": "https://sec.thief.one/article_content?a_id=c75700bf9e867354c54842800fa0907d",
        "date": "2021-03-17"
      },
      {
        "title": "Apache Solr 组件安全概览",
        "link": "https://sec.thief.one/article_content?a_id=d423fef990ddc35a22452dbf4db35f07",
        "date": "2021-03-17"
      },
      {
        "title": "新书上市《内生安全:新一代网络安全框架体系与实践》",
        "link": "https://sec.thief.one/article_content?a_id=1d4394149ca01dac47f877701c8300ef",
        "date": "2021-03-17"
      },
      {
        "title": "安全研究 | 多种方式利用HTTP PUT方法漏洞",
        "link": "https://sec.thief.one/article_content?a_id=b73dfd132c825f5f8ff05519bbf9dfcd",
        "date": "2021-03-17"
      },
      {
        "title": "假装很忙的2个命令行工具",
        "link": "https://sec.thief.one/article_content?a_id=1b61414010ebe9a352df9af6129c2cae",
        "date": "2021-03-17"
      },
      {
        "title": "后天见!",
        "link": "https://sec.thief.one/article_content?a_id=2f6914659996e64dc00dad621fe9bc3f",
        "date": "2021-03-17"
      },
      {
        "title": "牵手长亭,「目极千里 洞见安全」安全技术沙龙来了!",
        "link": "https://sec.thief.one/article_content?a_id=792e0ab33238d5c8a14a1802a517f105",
        "date": "2021-03-17"
      },
      {
        "title": "315曝光的侵犯个人信息行为可以用区块链来规范吗?",
        "link": "https://sec.thief.one/article_content?a_id=41f85ecd6fd0cd34ab7b0b1e70b71a8e",
        "date": "2021-03-17"
      },
      {
        "title": "【技术分享】Stop家族勒索病毒litar变种分析",
        "link": "https://sec.thief.one/article_content?a_id=f709e287ec0c365bffa30f83c2262ec1",
        "date": "2021-03-17"
      },
      {
        "title": "GoPro、Apple Watch、无人机,大礼已就绪,就等你露一手!",
        "link": "https://sec.thief.one/article_content?a_id=11ba684e0fd840bbdd7cb277ecb493c5",
        "date": "2021-03-17"
      },
      {
        "title": "易安联完成B+轮融资丨零信任安全",
        "link": "https://sec.thief.one/article_content?a_id=7eb4cfa1c987fcb4130868742de00998",
        "date": "2021-03-17"
      },
      {
        "title": "第三期字节跳动“安全范儿”沙龙来咯!",
        "link": "https://sec.thief.one/article_content?a_id=674f6147f8538a77ff56e5903bbe0ead",
        "date": "2021-03-17"
      },
      {
        "title": "诸子云|话题:如何应对供应链攻击?怎样落实数据存储加密?如何解密...",
        "link": "https://sec.thief.one/article_content?a_id=30c97b863b796a466f0ec4ced6a5900a",
        "date": "2021-03-17"
      },
      {
        "title": "HW干货集合 | HW面试题记录",
        "link": "https://sec.thief.one/article_content?a_id=076dcb2bdb45e9d2478c236f3f065249",
        "date": "2021-03-17"
      },
      {
        "title": "聚焦“315” | 简历信息泄露、人脸识别滥用、手机垃圾软件乱象",
        "link": "https://sec.thief.one/article_content?a_id=322e2a7f7819e1f80e989c29f255a798",
        "date": "2021-03-17"
      },
      {
        "title": "数字资产投资产品本季度流入资金创下42亿美元的新纪录",
        "link": "https://sec.thief.one/article_content?a_id=edb4d07af6e2d83d365e3e0e984e11da",
        "date": "2021-03-17"
      },
      {
        "title": "3月17日贵币GUIBI早内参-总价值超53亿美元的BTC期权即将到期,...",
        "link": "https://sec.thief.one/article_content?a_id=3e96466f518fd724e01af86e4292984e",
        "date": "2021-03-17"
      },
      {
        "title": "Microsoft 365服务中断,可能影响全球用户",
        "link": "https://sec.thief.one/article_content?a_id=079cf19d2fc2dd364a0f5e79f50fdfbf",
        "date": "2021-03-17"
      },
      {
        "title": "零信任安全领导厂商易安联完成B+轮融资 加速拓展全国市场",
        "link": "https://sec.thief.one/article_content?a_id=9b4ad568f354cb70eea152a55d34e60f",
        "date": "2021-03-17"
      },
      {
        "title": "2021年开发安全需求将爆炸式增长",
        "link": "https://sec.thief.one/article_content?a_id=8c9fc23fefeb8348366b90036bce4a27",
        "date": "2021-03-17"
      },
      {
        "title": "黑客将盗取的信用卡数据隐藏在JPG文件中",
        "link": "https://sec.thief.one/article_content?a_id=9cd1f0bd9e5673a9aa750678a8767f0e",
        "date": "2021-03-17"
      },
      {
        "title": "CVE-2021-21978:VM View Planner RCE分析复现",
        "link": "https://sec.thief.one/article_content?a_id=dc8eda27ab8fd390116c11138dea7715",
        "date": "2021-03-17"
      },
      {
        "title": "微软在美国新增网络支出中收获逾1.93亿美元",
        "link": "https://sec.thief.one/article_content?a_id=89b1c9f9f0b910d9a3a2cef89fb05540",
        "date": "2021-03-17"
      },
      {
        "title": "欧盟技术主权 | 《电子隐私条例》(e-Privacy Regulation)全文翻译",
        "link": "https://sec.thief.one/article_content?a_id=dddf97d84c02de43ef556177b5888b15",
        "date": "2021-03-17"
      },
      {
        "title": "计算机科学界至今未解决的四大难题",
        "link": "https://sec.thief.one/article_content?a_id=89d383d8d58e06c7ae481e8de03c3322",
        "date": "2021-03-17"
      },
      {
        "title": "Linux再次被爆root提权漏洞,已存在长达15年之久!",
        "link": "https://sec.thief.one/article_content?a_id=70d2e72d0a36dc06e0ba7bf088a1e485",
        "date": "2021-03-17"
      },
      {
        "title": "【游戏安全】给抓猫游戏开天劫",
        "link": "https://sec.thief.one/article_content?a_id=0e6699f9098fa441fa0f5bf65ba7aeaa",
        "date": "2021-03-17"
      },
      {
        "title": "工程师姓什么很重要!别再叫我“X工”!!!",
        "link": "https://sec.thief.one/article_content?a_id=f3cb8160b3fb4380a04465af971d128f",
        "date": "2021-03-17"
      },
      {
        "title": "微步在线完成E轮5亿元融资,半年内合计融资8亿元!",
        "link": "https://sec.thief.one/article_content?a_id=55597256fa4169a28e1478b09e9d685a",
        "date": "2021-03-17"
      },
      {
        "title": "网络安全编程:内核文件的读写",
        "link": "https://sec.thief.one/article_content?a_id=6e999cef151e577d9cd9a9c0f3048cb3",
        "date": "2021-03-17"
      },
      {
        "title": "党史学习教育“指定书目”来了,为啥是这四本?",
        "link": "https://sec.thief.one/article_content?a_id=72ec9a2e6151f8b55d6e059fa23b14e3",
        "date": "2021-03-17"
      },
      {
        "title": "2020年网络犯罪人数激增47.9% ,数据合规成企业命门",
        "link": "https://sec.thief.one/article_content?a_id=35e21033bf7cd4676102b662feae3807",
        "date": "2021-03-17"
      },
      {
        "title": "市场监管总局《网络交易监督管理办法》全文及官方解读",
        "link": "https://sec.thief.one/article_content?a_id=f0ef3099ed0875c57c096302d573d5f5",
        "date": "2021-03-17"
      },
      {
        "title": "日媒前往中国刺探军情",
        "link": "https://sec.thief.one/article_content?a_id=17ce507eb3250c68cca4f8be16288e6f",
        "date": "2021-03-16"
      },
      {
        "title": "【安全圈】Linux再次被爆root提权漏洞,已存在长达15年之久!",
        "link": "https://sec.thief.one/article_content?a_id=7c1f1a53acc5b7673b211a8dd23a20d3",
        "date": "2021-03-16"
      },
      {
        "title": "每日攻防资讯简报[Mar.16th]",
        "link": "https://sec.thief.one/article_content?a_id=81cb706d6a73ec49e165594cb2d6156e",
        "date": "2021-03-16"
      },
      {
        "title": "为什么不要轻易使用 Chrome 复制的 XPath?",
        "link": "https://sec.thief.one/article_content?a_id=6af88bb7c6d43797bf9452c9f7a785aa",
        "date": "2021-03-16"
      },
      {
        "title": "试用期没过,因在公司上了 1024 网站...",
        "link": "https://sec.thief.one/article_content?a_id=66fd22db25f4357a99febefdcf99efe9",
        "date": "2021-03-16"
      },
      {
        "title": "第二届“网安好播客”直播大赛启动报名",
        "link": "https://sec.thief.one/article_content?a_id=9081c52a8e3f995de1ac42d3018243e4",
        "date": "2021-03-16"
      },
      {
        "title": "西湖边 课堂前|《数据安全实践专题培训》即将开课",
        "link": "https://sec.thief.one/article_content?a_id=3052209226a7a68250a6d51eadacc137",
        "date": "2021-03-16"
      },
      {
        "title": "深度解读|全国最繁忙机场是如何建设网络安全的?",
        "link": "https://sec.thief.one/article_content?a_id=567d94e53dbb4c5fe655d825fc22bb1d",
        "date": "2021-03-16"
      },
      {
        "title": "Microsoft 365服务中断,可能影响全球用户",
        "link": "https://sec.thief.one/article_content?a_id=3908904c64bf0f9e2d8f7d275c92d1fd",
        "date": "2021-03-16"
      },
      {
        "title": "春日招聘|网易、小米十个岗位热招中",
        "link": "https://sec.thief.one/article_content?a_id=12def8655a36ed5a97d1f4a334c533a6",
        "date": "2021-03-16"
      },
      {
        "title": "【安全头条】比特币飙升显卡陪跑,限速被破或再临涨价潮",
        "link": "https://sec.thief.one/article_content?a_id=e7e944d4f00376c121a4614f135d9361",
        "date": "2021-03-16"
      },
      {
        "title": "干货 |GitHUB安全搬运工 七",
        "link": "https://sec.thief.one/article_content?a_id=b71041c296b9c5f70842fd0c1cb3f498",
        "date": "2021-03-16"
      },
      {
        "title": "703亿次抖音春晚红包背后的故事",
        "link": "https://sec.thief.one/article_content?a_id=bfef5efcc5366104cef976688bc7d971",
        "date": "2021-03-16"
      },
      {
        "title": "信息安全漏洞周报(2021年第11期)",
        "link": "https://sec.thief.one/article_content?a_id=3d42e7d45cff2fe0f1fff99ddca7585d",
        "date": "2021-03-16"
      },
      {
        "title": "谷歌、苹果、微软纷纷禁用它,第三方Cookie该何去何从?",
        "link": "https://sec.thief.one/article_content?a_id=1cb65c989974d605194a718f53102a7b",
        "date": "2021-03-16"
      },
      {
        "title": "安全资讯| Microsoft 365服务中断,可能影响全球用户!",
        "link": "https://sec.thief.one/article_content?a_id=7d810a0ff506eaebfe8e4f68bafe48cb",
        "date": "2021-03-16"
      },
      {
        "title": "2021年2月份奖励公告",
        "link": "https://sec.thief.one/article_content?a_id=f3d7d66c1acff471002b27eb966b920e",
        "date": "2021-03-16"
      },
      {
        "title": "信安十年,进入人生下一个阶段",
        "link": "https://sec.thief.one/article_content?a_id=3fffbcef7314e3b87aa1dc25251fe7f6",
        "date": "2021-03-16"
      },
      {
        "title": "蓝队防守必须排查的57个安全漏洞与解决方案",
        "link": "https://sec.thief.one/article_content?a_id=4e21ce9f414fda5ee1f6e3b7fe68b00d",
        "date": "2021-03-16"
      },
      {
        "title": "3月16日贵币GUIBI早内参-马斯克将职位头衔改为“特斯拉电音之王”...",
        "link": "https://sec.thief.one/article_content?a_id=859a68cf6c81ac6e357c0601c2b90dae",
        "date": "2021-03-16"
      },
      {
        "title": "从网络空间国际准则看国际关键信息基础设施保护及启示建议",
        "link": "https://sec.thief.one/article_content?a_id=4ccae9bf2f597a0ec2dd2c65b00579e1",
        "date": "2021-03-16"
      },
      {
        "title": "快快看过来!Microsoft Exchange Server漏洞迄今为止最全面的修复信...",
        "link": "https://sec.thief.one/article_content?a_id=a76c68e38f485a538bb6fd746b7a955b",
        "date": "2021-03-16"
      },
      {
        "title": "《网络交易监督管理办法》全文及答记者问",
        "link": "https://sec.thief.one/article_content?a_id=9c2f950f3acfcd28fa0f826ccddd9166",
        "date": "2021-03-16"
      },
      {
        "title": "【通告更新】微软发布漏洞本地缓解工具EOMT,Microsoft Exchange多...",
        "link": "https://sec.thief.one/article_content?a_id=96d97427b3096607e868ba90f74a6460",
        "date": "2021-03-16"
      },
      {
        "title": "任何人都可以利用!研究人员发现微软Exchange新漏洞",
        "link": "https://sec.thief.one/article_content?a_id=a7dcb2ee2cdf29642cb72b5ad290f69d",
        "date": "2021-03-16"
      },
      {
        "title": "【PC样本分析】记录最近与挖矿病毒的斗智斗勇(二)",
        "link": "https://sec.thief.one/article_content?a_id=89fc07a7ca051f986ce7750710ebc2ef",
        "date": "2021-03-16"
      },
      {
        "title": "巧用SSH转发功能深入穿透内网",
        "link": "https://sec.thief.one/article_content?a_id=dbd9a040ffe3a0b75f43641e9be0b1e0",
        "date": "2021-03-16"
      }
    ]
  },
  {
    "rss": "https://front-rss.herokuapp.com/wechat/ershicimi/PQDgZ2jW",
    "title": "物联网智库",
    "link": "https://www.ershicimi.com/a/PQDgZ2jW",
    "items": [
      {
        "title": "高中校园高科技黑板走红！无需粉笔，教师们直接撸袖子上手了......",
        "link": "https://www.ershicimi.com/p/b865f3b70446f5db276788b6f7b90a59",
        "date": "2021-03-01"
      },
      {
        "title": "【直播报名】物联网数据4.0时代，企业还有哪些新的存储需求？",
        "link": "https://www.ershicimi.com/p/38cd58ec7eba50794e472b524952553c",
        "date": "2021-03-01"
      },
      {
        "title": "物联网时代需要“小而灵”的企业，创通联达“5G+AI+边缘计算”推动企业数字化变革",
        "link": "https://www.ershicimi.com/p/66745320769f9c84b911e004b1809f82",
        "date": "2021-03-01"
      },
      {
        "title": "第一次，工业自动化界推进同一种无线通讯标准【物女心经】",
        "link": "https://www.ershicimi.com/p/b8314525d64036890b48844566216ee5",
        "date": "2021-02-28"
      },
      {
        "title": "物联网投融资周报|摩尔线程完成数十亿元融资；小马智行完成3.67亿美元融资；黑湖智造完成近5亿元融资",
        "link": "https://www.ershicimi.com/p/e2ab11f8855aadf53994027256126510",
        "date": "2021-02-28"
      },
      {
        "title": "5G没有“它”，就像盖房子没有土地一样",
        "link": "https://www.ershicimi.com/p/50ba83a78e3c3950bee3ef748b342517",
        "date": "2021-02-27"
      },
      {
        "title": "Gartner发布5G网络基础设施魔力象限报告",
        "link": "https://www.ershicimi.com/p/f3f20bfd0cbff0733692c591aa267f18",
        "date": "2021-02-27"
      },
      {
        "title": "中国网友大规模组建家庭式矿场，韩国两成网吧关门挖比特币，游戏玩家：求求你们别抢我的GPU了……",
        "link": "https://www.ershicimi.com/p/63a6442f40c53e453577d16fff3cfd16",
        "date": "2021-02-26"
      },
      {
        "title": "2021MWC上海展强势回归，广和通5力全开，惊艳亮相",
        "link": "https://www.ershicimi.com/p/4c11049507813b13f1345c465d0ccc09",
        "date": "2021-02-26"
      },
      {
        "title": "2020全球CEO年薪大榜：劈柴哥年入2.8亿美元登顶",
        "link": "https://www.ershicimi.com/p/b21bb459567359977524a2a93fcbacc7",
        "date": "2021-02-26"
      },
      {
        "title": "鸡蛋从25楼抛下便可致死，华为/海康/宇视…如何解决悬在城市上空的痛？",
        "link": "https://www.ershicimi.com/p/73274e42874653af529dcb40bd997f87",
        "date": "2021-02-25"
      },
      {
        "title": "芯片供需缺口或达30%？刚刚，拜登正式签署行政令解决半导体芯片短缺问题",
        "link": "https://www.ershicimi.com/p/546a972b0ddce5e493c873c4170b2140",
        "date": "2021-02-25"
      },
      {
        "title": "沉寂多年的十大物联网操作系统之一Fuchsia频曝新消息",
        "link": "https://www.ershicimi.com/p/4d3461f2863cbc5cba3817e5543b8d62",
        "date": "2021-02-25"
      },
      {
        "title": "芯讯通一口气发布5款模组，蜂窝物联网模组厂商如何构建万物互联大时代？",
        "link": "https://www.ershicimi.com/p/1690a236c67604d827d8064cbfa84bff",
        "date": "2021-02-24"
      },
      {
        "title": "云网融合为啥这么火？",
        "link": "https://www.ershicimi.com/p/bfbb84774ca7c39b1cc1d06de139abb9",
        "date": "2021-02-24"
      },
      {
        "title": "大白天「撞鬼」？特斯拉在无人墓地感应到行人，传感器真能测鬼？",
        "link": "https://www.ershicimi.com/p/d78403cc2920d0df96898e983c21bb9d",
        "date": "2021-02-24"
      },
      {
        "title": "移远通信发布5G智能模组，终端战场上再添“新火器”",
        "link": "https://www.ershicimi.com/p/585b3175dd111b4960c29e9265dd431c",
        "date": "2021-02-23"
      },
      {
        "title": "IOTE国际物联网展！ 六大展区将为您展示物联网头部企业新产品、新科技，挖掘物联网亿万市场！",
        "link": "https://www.ershicimi.com/p/af4c8461c5b5932b4f4da003fa84d884",
        "date": "2021-02-23"
      },
      {
        "title": "智能家居的“战火”，从“后装”烧到了“前装”市场",
        "link": "https://www.ershicimi.com/p/de67820444f7cd6c0e68ab36816bcee3",
        "date": "2021-02-23"
      },
      {
        "title": "售价17999起，华为史上最强折叠机皇Mate X2来了！双螺旋水滴铰链，首批升级鸿蒙OS",
        "link": "https://www.ershicimi.com/p/c282026871532dca38366009aa81bafb",
        "date": "2021-02-22"
      }
    ]
  }
]